icotools/__init__.py
icotools/foiler.py
icotools/guesser.py
icotools/rater.py
icotools/features/phoible-segments-features.tsv
icotools/templates/guesses_images.html
icotools/templates/guesses_mp3.html
icotools/templates/guesses_mp4.html
icotools/templates/php_temp.php
icotools/templates/ratings_images.html
icotools/templates/ratings_mp3.html
icotools/templates/ratings_mp4.html
icotools-1.2.3.dist-info/LICENSE
icotools-1.2.3.dist-info/METADATA
icotools-1.2.3.dist-info/WHEEL
icotools-1.2.3.dist-info/top_level.txt
icotools-1.2.3.dist-info/RECORD
