Metadata-Version: 2.1
Name: icotools
Version: 1.2.3
Summary: Tools for collecting behavioural measures of iconicity
Home-page: https://pypi.org/project/icotools/
Author: Bonnie McLean
Author-email: <59.b.mclean@gmail.com>
License: LICENSE
Keywords: python,iconicity
Classifier: Development Status :: 3 - Alpha
Classifier: Intended Audience :: Education
Classifier: Programming Language :: Python :: 3
Classifier: Operating System :: MacOS :: MacOS X
Classifier: Operating System :: Microsoft :: Windows
License-File: LICENSE
